rmsyutls/__init__.py
rmsyutls/_src/__init__.py
rmsyutls/_src/iterator.py
rmsyutls/_src/test_rmsy_utls.py
rmsyutls-0.0.2.dist-info/METADATA
rmsyutls-0.0.2.dist-info/WHEEL
rmsyutls-0.0.2.dist-info/licenses/LICENSE
rmsyutls-0.0.2.dist-info/RECORD
