Metadata-Version: 2.1
Name: rmsyutls
Version: 0.0.2
Summary: Utility functions for Ramsey
Project-URL: homepage, https://github.com/ramsey-devs/rmsy-utls
Author-email: Simon Dirmeier <sfyrbnd@pm.me>
License-Expression: Apache-2.0
License-File: LICENSE
Classifier: Development Status :: 1 - Planning
Classifier: Intended Audience :: Science/Research
Classifier: License :: OSI Approved :: Apache Software License
Classifier: Programming Language :: Python :: 3
Classifier: Programming Language :: Python :: 3.8
Classifier: Programming Language :: Python :: 3.9
Requires-Python: >=3.8
Requires-Dist: chex>=0.1.5
Requires-Dist: jax>=0.4.5
